Metadata-Version: 2.1
Name: F1bw
Version: 0.2.1
Summary: UNKNOWN
Home-page: http://github.com/MChigaev/F1bw
Author: Michael Chigaev
Author-email: mikechigaev@gmail.com
Maintainer: Michael Chigaev
Maintainer-email: mikechigaev@gmail.com
License: BSD 3-Clause License
Keywords: science,biology,bioinformatics,genes,compression,burrows-wheeler
Platform: UNKNOWN
Classifier: Development Status :: 3 - Alpha
Classifier: Environment :: Console
Classifier: Intended Audience :: Science/Research
Classifier: License :: OSI Approved :: BSD License
Classifier: Operating System :: MacOS :: MacOS X
Classifier: Operating System :: POSIX :: Linux
Classifier: Operating System :: POSIX :: BSD
Classifier: Programming Language :: Python :: 3.4
Classifier: Programming Language :: Python :: 3.5
Classifier: Programming Language :: Python :: 3.6
Classifier: Topic :: Scientific/Engineering :: Bio-Informatics
Provides-Extra: all
Provides-Extra: tests
Provides-Extra: docs
